{
  "meta": {
    "stock_id": "1722",
    "name": "台肥",
    "source": "TWSE daily (twse/2026/)",
    "period": "~40 trading days",
    "date_range": "20260410~20260605",
    "count": 40,
    "format_note": "AI-readable OHLC data. date(YYYY/MM/DD), open/high/low/close(float), volume(int, 張). Bullish=close>open, Bearish=close<open."
  },
  "data": [
    {
      "date": "2026/06/05",
      "open": 48.6,
      "high": 48.65,
      "low": 47.6,
      "close": 48.25,
      "volume": 5612,
      "MA5": 47.67,
      "MA10": 46.84,
      "MA20": 46.55
    },
    {
      "date": "2026/06/04",
      "open": 47.85,
      "high": 48.35,
      "low": 47.75,
      "close": 48.05,
      "volume": 4792,
      "MA5": 47.34,
      "MA10": 46.61,
      "MA20": 46.46
    },
    {
      "date": "2026/06/03",
      "open": 47.25,
      "high": 48.4,
      "low": 46.9,
      "close": 47.95,
      "volume": 6745,
      "MA5": 46.95,
      "MA10": 46.44,
      "MA20": 46.4
    },
    {
      "date": "2026/06/02",
      "open": 47.0,
      "high": 47.3,
      "low": 46.8,
      "close": 47.05,
      "volume": 2691,
      "MA5": 46.49,
      "MA10": 46.21,
      "MA20": 46.35
    },
    {
      "date": "2026/06/01",
      "open": 46.6,
      "high": 47.2,
      "low": 46.1,
      "close": 47.05,
      "volume": 4239,
      "MA5": 46.24,
      "MA10": 46.07,
      "MA20": 46.34
    },
    {
      "date": "2026/05/29",
      "open": 46.4,
      "high": 46.6,
      "low": 46.05,
      "close": 46.6,
      "volume": 2427,
      "MA5": 46.0,
      "MA10": 45.91,
      "MA20": 46.41
    },
    {
      "date": "2026/05/28",
      "open": 46.5,
      "high": 46.8,
      "low": 46.0,
      "close": 46.1,
      "volume": 3992,
      "MA5": 45.89,
      "MA10": 45.83,
      "MA20": 46.61
    },
    {
      "date": "2026/05/27",
      "open": 45.85,
      "high": 45.95,
      "low": 45.35,
      "close": 45.65,
      "volume": 3501,
      "MA5": 45.92,
      "MA10": 45.91,
      "MA20": 46.74
    },
    {
      "date": "2026/05/26",
      "open": 45.85,
      "high": 46.35,
      "low": 45.8,
      "close": 45.8,
      "volume": 2014,
      "MA5": 45.94,
      "MA10": 46.02,
      "MA20": 46.67
    },
    {
      "date": "2026/05/25",
      "open": 46.15,
      "high": 46.2,
      "low": 45.7,
      "close": 45.85,
      "volume": 3051,
      "MA5": 45.9,
      "MA10": 46.14,
      "MA20": 46.59
    },
    {
      "date": "2026/05/22",
      "open": 46.25,
      "high": 46.4,
      "low": 45.9,
      "close": 46.05,
      "volume": 1997,
      "MA5": 45.82,
      "MA10": 46.27,
      "MA20": 46.52
    },
    {
      "date": "2026/05/21",
      "open": 45.85,
      "high": 46.4,
      "low": 45.7,
      "close": 46.25,
      "volume": 1808,
      "MA5": 45.76,
      "MA10": 46.31,
      "MA20": 46.45
    },
    {
      "date": "2026/05/20",
      "open": 46.0,
      "high": 46.1,
      "low": 45.35,
      "close": 45.75,
      "volume": 2332,
      "MA5": 45.91,
      "MA10": 46.37,
      "MA20": 46.39
    },
    {
      "date": "2026/05/19",
      "open": 45.9,
      "high": 46.1,
      "low": 45.6,
      "close": 45.6,
      "volume": 2306,
      "MA5": 46.1,
      "MA10": 46.48,
      "MA20": 46.35
    },
    {
      "date": "2026/05/18",
      "open": 45.2,
      "high": 45.7,
      "low": 45.15,
      "close": 45.45,
      "volume": 2663,
      "MA5": 46.38,
      "MA10": 46.62,
      "MA20": 46.34
    },
    {
      "date": "2026/05/15",
      "open": 47.0,
      "high": 47.05,
      "low": 45.65,
      "close": 45.75,
      "volume": 7484,
      "MA5": 46.71,
      "MA10": 46.9,
      "MA20": 46.34
    },
    {
      "date": "2026/05/14",
      "open": 46.8,
      "high": 47.3,
      "low": 46.5,
      "close": 47.0,
      "volume": 3527,
      "MA5": 46.87,
      "MA10": 47.39,
      "MA20": 46.34
    },
    {
      "date": "2026/05/13",
      "open": 47.0,
      "high": 47.25,
      "low": 46.7,
      "close": 46.7,
      "volume": 2859,
      "MA5": 46.83,
      "MA10": 47.56,
      "MA20": 46.28
    },
    {
      "date": "2026/05/12",
      "open": 47.65,
      "high": 47.75,
      "low": 46.95,
      "close": 47.0,
      "volume": 4638,
      "MA5": 46.86,
      "MA10": 47.33,
      "MA20": 46.27
    },
    {
      "date": "2026/05/11",
      "open": 46.9,
      "high": 47.5,
      "low": 46.85,
      "close": 47.1,
      "volume": 4403,
      "MA5": 46.86,
      "MA10": 47.05,
      "MA20": 46.27
    },
    {
      "date": "2026/05/08",
      "open": 47.2,
      "high": 47.2,
      "low": 46.55,
      "close": 46.55,
      "volume": 2754,
      "MA5": 47.09,
      "MA10": 46.78,
      "MA20": 46.23
    },
    {
      "date": "2026/05/07",
      "open": 46.9,
      "high": 47.85,
      "low": 46.45,
      "close": 46.8,
      "volume": 4965,
      "MA5": 47.92,
      "MA10": 46.59
    },
    {
      "date": "2026/05/06",
      "open": 47.05,
      "high": 47.55,
      "low": 46.55,
      "close": 46.85,
      "volume": 5231,
      "MA5": 48.3,
      "MA10": 46.4
    },
    {
      "date": "2026/05/05",
      "open": 48.0,
      "high": 48.0,
      "low": 46.85,
      "close": 47.0,
      "volume": 6882,
      "MA5": 47.79,
      "MA10": 46.23
    },
    {
      "date": "2026/05/04",
      "open": 49.9,
      "high": 49.9,
      "low": 48.2,
      "close": 48.25,
      "volume": 10146,
      "MA5": 47.24,
      "MA10": 46.05
    },
    {
      "date": "2026/04/30",
      "open": 51.0,
      "high": 52.0,
      "low": 49.0,
      "close": 50.7,
      "volume": 41863,
      "MA5": 46.47,
      "MA10": 45.79
    },
    {
      "date": "2026/04/29",
      "open": 47.1,
      "high": 48.7,
      "low": 46.15,
      "close": 48.7,
      "volume": 20006,
      "MA5": 45.25,
      "MA10": 45.29
    },
    {
      "date": "2026/04/28",
      "open": 44.15,
      "high": 44.6,
      "low": 44.15,
      "close": 44.3,
      "volume": 1106,
      "MA5": 44.5,
      "MA10": 44.99
    },
    {
      "date": "2026/04/27",
      "open": 44.3,
      "high": 44.45,
      "low": 44.05,
      "close": 44.25,
      "volume": 2411,
      "MA5": 44.66,
      "MA10": 45.21
    },
    {
      "date": "2026/04/24",
      "open": 44.75,
      "high": 44.75,
      "low": 44.4,
      "close": 44.4,
      "volume": 2689,
      "MA5": 44.86,
      "MA10": 45.48
    },
    {
      "date": "2026/04/23",
      "open": 44.95,
      "high": 45.0,
      "low": 44.4,
      "close": 44.6,
      "volume": 3734,
      "MA5": 45.11,
      "MA10": 45.67
    },
    {
      "date": "2026/04/22",
      "open": 45.1,
      "high": 45.2,
      "low": 44.85,
      "close": 44.95,
      "volume": 2785,
      "MA5": 45.32
    },
    {
      "date": "2026/04/21",
      "open": 45.45,
      "high": 45.45,
      "low": 45.05,
      "close": 45.1,
      "volume": 1895,
      "MA5": 45.48
    },
    {
      "date": "2026/04/20",
      "open": 45.65,
      "high": 45.75,
      "low": 45.25,
      "close": 45.25,
      "volume": 2761,
      "MA5": 45.77
    },
    {
      "date": "2026/04/17",
      "open": 45.9,
      "high": 46.0,
      "low": 45.4,
      "close": 45.65,
      "volume": 3237,
      "MA5": 46.11
    },
    {
      "date": "2026/04/16",
      "open": 45.75,
      "high": 45.9,
      "low": 45.6,
      "close": 45.65,
      "volume": 2250,
      "MA5": 46.24
    },
    {
      "date": "2026/04/15",
      "open": 46.5,
      "high": 46.5,
      "low": 45.7,
      "close": 45.75,
      "volume": 4201
    },
    {
      "date": "2026/04/14",
      "open": 46.95,
      "high": 47.0,
      "low": 46.3,
      "close": 46.55,
      "volume": 2599
    },
    {
      "date": "2026/04/13",
      "open": 46.65,
      "high": 47.25,
      "low": 46.55,
      "close": 46.95,
      "volume": 3675
    },
    {
      "date": "2026/04/10",
      "open": 46.8,
      "high": 46.8,
      "low": 46.05,
      "close": 46.3,
      "volume": 1525
    }
  ]
}