{
  "meta": {
    "stock_id": "1802",
    "name": "台玻",
    "source": "TWSE daily (twse/2026/)",
    "period": "~40 trading days",
    "date_range": "20260330~20260527",
    "count": 40,
    "format_note": "AI-readable OHLC data. date(YYYY/MM/DD), open/high/low/close(float), volume(int, 張). Bullish=close>open, Bearish=close<open."
  },
  "data": [
    {
      "date": "2026/05/27",
      "open": 73.0,
      "high": 74.4,
      "low": 70.2,
      "close": 72.8,
      "volume": 154134,
      "MA5": 70.9,
      "MA10": 68.04,
      "MA20": 68.62
    },
    {
      "date": "2026/05/26",
      "open": 75.0,
      "high": 81.2,
      "low": 72.0,
      "close": 72.2,
      "volume": 337055,
      "MA5": 69.12,
      "MA10": 67.56,
      "MA20": 68.52
    },
    {
      "date": "2026/05/25",
      "open": 73.0,
      "high": 76.8,
      "low": 71.9,
      "close": 73.9,
      "volume": 185285,
      "MA5": 67.74,
      "MA10": 67.45,
      "MA20": 68.11
    },
    {
      "date": "2026/05/22",
      "open": 67.1,
      "high": 70.6,
      "low": 67.0,
      "close": 70.5,
      "volume": 125407,
      "MA5": 65.92,
      "MA10": 67.05,
      "MA20": 67.67
    },
    {
      "date": "2026/05/21",
      "open": 65.0,
      "high": 67.6,
      "low": 65.0,
      "close": 65.1,
      "volume": 47676,
      "MA5": 64.82,
      "MA10": 66.89,
      "MA20": 67.45
    },
    {
      "date": "2026/05/20",
      "open": 65.7,
      "high": 66.0,
      "low": 63.3,
      "close": 63.9,
      "volume": 43798,
      "MA5": 65.18,
      "MA10": 67.46,
      "MA20": 67.75
    },
    {
      "date": "2026/05/19",
      "open": 65.3,
      "high": 69.0,
      "low": 64.6,
      "close": 65.3,
      "volume": 79999,
      "MA5": 66.0,
      "MA10": 68.19,
      "MA20": 68.26
    },
    {
      "date": "2026/05/18",
      "open": 64.3,
      "high": 65.2,
      "low": 61.8,
      "close": 64.8,
      "volume": 45175,
      "MA5": 67.16,
      "MA10": 68.94,
      "MA20": 68.54
    },
    {
      "date": "2026/05/15",
      "open": 67.2,
      "high": 68.6,
      "low": 64.6,
      "close": 65.0,
      "volume": 69667,
      "MA5": 68.18,
      "MA10": 69.08,
      "MA20": 69.01
    },
    {
      "date": "2026/05/14",
      "open": 68.6,
      "high": 69.2,
      "low": 66.5,
      "close": 66.9,
      "volume": 65655,
      "MA5": 68.96,
      "MA10": 69.28,
      "MA20": 69.26
    },
    {
      "date": "2026/05/13",
      "open": 70.0,
      "high": 70.1,
      "low": 68.0,
      "close": 68.0,
      "volume": 60464,
      "MA5": 69.74,
      "MA10": 69.21,
      "MA20": 69.37
    },
    {
      "date": "2026/05/12",
      "open": 70.5,
      "high": 73.4,
      "low": 70.0,
      "close": 71.1,
      "volume": 132631,
      "MA5": 70.38,
      "MA10": 69.47,
      "MA20": 69.38
    },
    {
      "date": "2026/05/11",
      "open": 69.0,
      "high": 70.2,
      "low": 67.7,
      "close": 69.9,
      "volume": 78048,
      "MA5": 70.72,
      "MA10": 68.78,
      "MA20": 69.0
    },
    {
      "date": "2026/05/08",
      "open": 71.4,
      "high": 71.8,
      "low": 67.3,
      "close": 68.9,
      "volume": 84842,
      "MA5": 69.98,
      "MA10": 68.29,
      "MA20": 68.39
    },
    {
      "date": "2026/05/07",
      "open": 72.6,
      "high": 75.0,
      "low": 70.7,
      "close": 70.8,
      "volume": 148214,
      "MA5": 69.6,
      "MA10": 68.02,
      "MA20": 67.92
    },
    {
      "date": "2026/05/06",
      "open": 73.8,
      "high": 75.5,
      "low": 69.4,
      "close": 71.2,
      "volume": 245896,
      "MA5": 68.68,
      "MA10": 68.03,
      "MA20": 67.33
    },
    {
      "date": "2026/05/05",
      "open": 66.3,
      "high": 72.8,
      "low": 66.1,
      "close": 72.8,
      "volume": 141172,
      "MA5": 68.56,
      "MA10": 68.33,
      "MA20": 66.45
    },
    {
      "date": "2026/05/04",
      "open": 68.0,
      "high": 68.9,
      "low": 66.1,
      "close": 66.2,
      "volume": 79575,
      "MA5": 66.84,
      "MA10": 68.14,
      "MA20": 65.42
    },
    {
      "date": "2026/04/30",
      "open": 66.3,
      "high": 69.3,
      "low": 65.3,
      "close": 67.0,
      "volume": 126951,
      "MA5": 66.6,
      "MA10": 68.94,
      "MA20": 64.81
    },
    {
      "date": "2026/04/29",
      "open": 68.9,
      "high": 69.4,
      "low": 66.1,
      "close": 66.2,
      "volume": 136201,
      "MA5": 66.44,
      "MA10": 69.23,
      "MA20": 64.05
    },
    {
      "date": "2026/04/28",
      "open": 64.1,
      "high": 70.6,
      "low": 63.5,
      "close": 70.6,
      "volume": 125945,
      "MA5": 67.38,
      "MA10": 69.53,
      "MA20": 63.46
    },
    {
      "date": "2026/04/27",
      "open": 65.0,
      "high": 65.5,
      "low": 61.7,
      "close": 64.2,
      "volume": 90057,
      "MA5": 68.1,
      "MA10": 69.29
    },
    {
      "date": "2026/04/24",
      "open": 67.6,
      "high": 67.8,
      "low": 63.1,
      "close": 65.0,
      "volume": 122228,
      "MA5": 69.44,
      "MA10": 69.21
    },
    {
      "date": "2026/04/23",
      "open": 71.6,
      "high": 72.5,
      "low": 64.7,
      "close": 66.2,
      "volume": 163064,
      "MA5": 71.28,
      "MA10": 68.48
    },
    {
      "date": "2026/04/22",
      "open": 74.5,
      "high": 76.9,
      "low": 70.8,
      "close": 70.9,
      "volume": 201510,
      "MA5": 72.02,
      "MA10": 67.81
    },
    {
      "date": "2026/04/21",
      "open": 71.4,
      "high": 75.5,
      "low": 71.3,
      "close": 74.2,
      "volume": 190381,
      "MA5": 71.68,
      "MA10": 66.62
    },
    {
      "date": "2026/04/20",
      "open": 75.5,
      "high": 76.0,
      "low": 70.4,
      "close": 70.9,
      "volume": 262065,
      "MA5": 70.48,
      "MA10": 64.57
    },
    {
      "date": "2026/04/17",
      "open": 69.2,
      "high": 76.6,
      "low": 69.1,
      "close": 74.2,
      "volume": 346753,
      "MA5": 68.98,
      "MA10": 62.7
    },
    {
      "date": "2026/04/16",
      "open": 70.5,
      "high": 72.8,
      "low": 66.0,
      "close": 69.9,
      "volume": 241025,
      "MA5": 65.68,
      "MA10": 60.67
    },
    {
      "date": "2026/04/15",
      "open": 69.8,
      "high": 71.0,
      "low": 65.4,
      "close": 69.2,
      "volume": 279186,
      "MA5": 63.6,
      "MA10": 58.87
    },
    {
      "date": "2026/04/14",
      "open": 64.9,
      "high": 69.5,
      "low": 64.7,
      "close": 68.2,
      "volume": 292052,
      "MA5": 61.56,
      "MA10": 57.39
    },
    {
      "date": "2026/04/13",
      "open": 58.8,
      "high": 63.4,
      "low": 58.2,
      "close": 63.4,
      "volume": 122615,
      "MA5": 58.66
    },
    {
      "date": "2026/04/10",
      "open": 62.1,
      "high": 62.5,
      "low": 57.4,
      "close": 57.7,
      "volume": 76142,
      "MA5": 56.42
    },
    {
      "date": "2026/04/09",
      "open": 61.5,
      "high": 64.5,
      "low": 59.2,
      "close": 59.5,
      "volume": 203015,
      "MA5": 55.66
    },
    {
      "date": "2026/04/08",
      "open": 56.0,
      "high": 59.0,
      "low": 56.0,
      "close": 59.0,
      "volume": 54516,
      "MA5": 54.14
    },
    {
      "date": "2026/04/07",
      "open": 53.8,
      "high": 55.0,
      "low": 52.9,
      "close": 53.7,
      "volume": 36938,
      "MA5": 53.22
    },
    {
      "date": "2026/04/02",
      "open": 54.5,
      "high": 55.6,
      "low": 52.0,
      "close": 52.2,
      "volume": 48195
    },
    {
      "date": "2026/04/01",
      "open": 54.1,
      "high": 55.4,
      "low": 53.5,
      "close": 53.9,
      "volume": 55082
    },
    {
      "date": "2026/03/31",
      "open": 53.4,
      "high": 57.0,
      "low": 51.0,
      "close": 51.9,
      "volume": 60205
    },
    {
      "date": "2026/03/30",
      "open": 53.0,
      "high": 54.4,
      "low": 52.3,
      "close": 54.4,
      "volume": 34286
    }
  ]
}