{
  "meta": {
    "stock_id": "2007",
    "name": "燁興",
    "source": "TWSE daily (twse/2026/)",
    "period": "~40 trading days",
    "date_range": "20260408~20260603",
    "count": 40,
    "format_note": "AI-readable OHLC data. date(YYYY/MM/DD), open/high/low/close(float), volume(int, 張). Bullish=close>open, Bearish=close<open."
  },
  "data": [
    {
      "date": "2026/06/03",
      "open": 7.52,
      "high": 8.15,
      "low": 7.51,
      "close": 7.99,
      "volume": 1798,
      "MA5": 7.63,
      "MA10": 7.48,
      "MA20": 7.31
    },
    {
      "date": "2026/06/02",
      "open": 7.74,
      "high": 7.74,
      "low": 7.52,
      "close": 7.6,
      "volume": 461,
      "MA5": 7.52,
      "MA10": 7.38,
      "MA20": 7.28
    },
    {
      "date": "2026/06/01",
      "open": 7.51,
      "high": 7.67,
      "low": 7.45,
      "close": 7.64,
      "volume": 733,
      "MA5": 7.52,
      "MA10": 7.3,
      "MA20": 7.27
    },
    {
      "date": "2026/05/29",
      "open": 7.49,
      "high": 7.58,
      "low": 7.42,
      "close": 7.5,
      "volume": 452,
      "MA5": 7.52,
      "MA10": 7.23,
      "MA20": 7.25
    },
    {
      "date": "2026/05/28",
      "open": 7.44,
      "high": 7.66,
      "low": 7.4,
      "close": 7.41,
      "volume": 334,
      "MA5": 7.42,
      "MA10": 7.18,
      "MA20": 7.25
    },
    {
      "date": "2026/05/27",
      "open": 7.51,
      "high": 7.68,
      "low": 7.42,
      "close": 7.44,
      "volume": 581,
      "MA5": 7.33,
      "MA10": 7.14,
      "MA20": 7.27
    },
    {
      "date": "2026/05/26",
      "open": 8.14,
      "high": 8.15,
      "low": 7.57,
      "close": 7.6,
      "volume": 1845,
      "MA5": 7.23,
      "MA10": 7.12,
      "MA20": 7.27
    },
    {
      "date": "2026/05/25",
      "open": 7.04,
      "high": 7.66,
      "low": 7.03,
      "close": 7.66,
      "volume": 1444,
      "MA5": 7.09,
      "MA10": 7.09,
      "MA20": 7.26
    },
    {
      "date": "2026/05/22",
      "open": 7.0,
      "high": 7.0,
      "low": 6.93,
      "close": 6.97,
      "volume": 243,
      "MA5": 6.93,
      "MA10": 7.06,
      "MA20": 7.25
    },
    {
      "date": "2026/05/21",
      "open": 6.93,
      "high": 7.14,
      "low": 6.93,
      "close": 7.0,
      "volume": 304,
      "MA5": 6.94,
      "MA10": 7.1,
      "MA20": 7.29
    },
    {
      "date": "2026/05/20",
      "open": 6.88,
      "high": 6.95,
      "low": 6.86,
      "close": 6.93,
      "volume": 199,
      "MA5": 6.95,
      "MA10": 7.13,
      "MA20": 7.34
    },
    {
      "date": "2026/05/19",
      "open": 6.88,
      "high": 6.97,
      "low": 6.86,
      "close": 6.88,
      "volume": 213,
      "MA5": 7.01,
      "MA10": 7.18,
      "MA20": 7.39
    },
    {
      "date": "2026/05/18",
      "open": 6.96,
      "high": 6.96,
      "low": 6.89,
      "close": 6.89,
      "volume": 409,
      "MA5": 7.09,
      "MA10": 7.23,
      "MA20": 7.44
    },
    {
      "date": "2026/05/15",
      "open": 7.1,
      "high": 7.1,
      "low": 6.98,
      "close": 6.98,
      "volume": 553,
      "MA5": 7.18,
      "MA10": 7.28,
      "MA20": 7.5
    },
    {
      "date": "2026/05/14",
      "open": 6.95,
      "high": 7.18,
      "low": 6.95,
      "close": 7.08,
      "volume": 427,
      "MA5": 7.26,
      "MA10": 7.33,
      "MA20": 7.55
    },
    {
      "date": "2026/05/13",
      "open": 7.33,
      "high": 7.33,
      "low": 7.2,
      "close": 7.23,
      "volume": 303,
      "MA5": 7.32,
      "MA10": 7.39,
      "MA20": 7.6
    },
    {
      "date": "2026/05/12",
      "open": 7.32,
      "high": 7.39,
      "low": 7.25,
      "close": 7.28,
      "volume": 382,
      "MA5": 7.35,
      "MA10": 7.42,
      "MA20": 7.64
    },
    {
      "date": "2026/05/11",
      "open": 7.37,
      "high": 7.49,
      "low": 7.32,
      "close": 7.32,
      "volume": 358,
      "MA5": 7.37,
      "MA10": 7.43,
      "MA20": 7.68
    },
    {
      "date": "2026/05/08",
      "open": 7.38,
      "high": 7.4,
      "low": 7.28,
      "close": 7.37,
      "volume": 426,
      "MA5": 7.38,
      "MA10": 7.45,
      "MA20": 7.72
    },
    {
      "date": "2026/05/07",
      "open": 7.3,
      "high": 7.41,
      "low": 7.3,
      "close": 7.38,
      "volume": 272,
      "MA5": 7.4,
      "MA10": 7.48,
      "MA20": 7.75
    },
    {
      "date": "2026/05/06",
      "open": 7.47,
      "high": 7.47,
      "low": 7.35,
      "close": 7.39,
      "volume": 453,
      "MA5": 7.47,
      "MA10": 7.54,
      "MA20": 7.78
    },
    {
      "date": "2026/05/05",
      "open": 7.4,
      "high": 7.46,
      "low": 7.35,
      "close": 7.37,
      "volume": 262,
      "MA5": 7.49,
      "MA10": 7.6
    },
    {
      "date": "2026/05/04",
      "open": 7.5,
      "high": 7.5,
      "low": 7.38,
      "close": 7.41,
      "volume": 422,
      "MA5": 7.5,
      "MA10": 7.66
    },
    {
      "date": "2026/04/30",
      "open": 7.74,
      "high": 7.74,
      "low": 7.45,
      "close": 7.46,
      "volume": 407,
      "MA5": 7.52,
      "MA10": 7.72
    },
    {
      "date": "2026/04/29",
      "open": 7.5,
      "high": 7.78,
      "low": 7.45,
      "close": 7.7,
      "volume": 650,
      "MA5": 7.56,
      "MA10": 7.78
    },
    {
      "date": "2026/04/28",
      "open": 7.42,
      "high": 7.6,
      "low": 7.41,
      "close": 7.5,
      "volume": 282,
      "MA5": 7.61,
      "MA10": 7.81
    },
    {
      "date": "2026/04/27",
      "open": 7.55,
      "high": 7.55,
      "low": 7.4,
      "close": 7.41,
      "volume": 609,
      "MA5": 7.72,
      "MA10": 7.86
    },
    {
      "date": "2026/04/24",
      "open": 7.66,
      "high": 7.66,
      "low": 7.5,
      "close": 7.54,
      "volume": 364,
      "MA5": 7.82,
      "MA10": 7.92
    },
    {
      "date": "2026/04/23",
      "open": 7.98,
      "high": 7.98,
      "low": 7.66,
      "close": 7.66,
      "volume": 451,
      "MA5": 7.91,
      "MA10": 7.98
    },
    {
      "date": "2026/04/22",
      "open": 8.04,
      "high": 8.04,
      "low": 7.9,
      "close": 7.93,
      "volume": 349,
      "MA5": 7.99,
      "MA10": 8.01
    },
    {
      "date": "2026/04/21",
      "open": 7.97,
      "high": 8.06,
      "low": 7.95,
      "close": 8.04,
      "volume": 421,
      "MA5": 8.01,
      "MA10": 8.03
    },
    {
      "date": "2026/04/20",
      "open": 8.0,
      "high": 8.01,
      "low": 7.9,
      "close": 7.94,
      "volume": 258,
      "MA5": 8.01
    },
    {
      "date": "2026/04/17",
      "open": 8.0,
      "high": 8.03,
      "low": 7.95,
      "close": 8.0,
      "volume": 306,
      "MA5": 8.03
    },
    {
      "date": "2026/04/16",
      "open": 8.01,
      "high": 8.07,
      "low": 7.98,
      "close": 8.03,
      "volume": 348,
      "MA5": 8.04
    },
    {
      "date": "2026/04/15",
      "open": 8.1,
      "high": 8.11,
      "low": 8.0,
      "close": 8.03,
      "volume": 486,
      "MA5": 8.04
    },
    {
      "date": "2026/04/14",
      "open": 8.02,
      "high": 8.11,
      "low": 7.99,
      "close": 8.05,
      "volume": 344,
      "MA5": 8.06
    },
    {
      "date": "2026/04/13",
      "open": 8.07,
      "high": 8.07,
      "low": 7.9,
      "close": 8.02,
      "volume": 294
    },
    {
      "date": "2026/04/10",
      "open": 8.09,
      "high": 8.19,
      "low": 8.03,
      "close": 8.07,
      "volume": 281
    },
    {
      "date": "2026/04/09",
      "open": 8.19,
      "high": 8.19,
      "low": 8.0,
      "close": 8.02,
      "volume": 246
    },
    {
      "date": "2026/04/08",
      "open": 7.96,
      "high": 8.17,
      "low": 7.96,
      "close": 8.12,
      "volume": 243
    }
  ]
}