{
  "meta": {
    "stock_id": "2881",
    "name": "富邦金",
    "source": "TWSE daily (twse/2026/)",
    "period": "~40 trading days",
    "date_range": "20260407~20260602",
    "count": 40,
    "format_note": "AI-readable OHLC data. date(YYYY/MM/DD), open/high/low/close(float), volume(int, 張). Bullish=close>open, Bearish=close<open."
  },
  "data": [
    {
      "date": "2026/06/02",
      "open": 110.5,
      "high": 113.5,
      "low": 109.0,
      "close": 113.5,
      "volume": 97486,
      "MA5": 110.8,
      "MA10": 104.22,
      "MA20": 99.66
    },
    {
      "date": "2026/06/01",
      "open": 109.5,
      "high": 112.0,
      "low": 107.0,
      "close": 110.5,
      "volume": 87579,
      "MA5": 108.8,
      "MA10": 102.59,
      "MA20": 98.59
    },
    {
      "date": "2026/05/29",
      "open": 110.5,
      "high": 111.0,
      "low": 107.0,
      "close": 110.0,
      "volume": 139031,
      "MA5": 106.24,
      "MA10": 101.06,
      "MA20": 97.62
    },
    {
      "date": "2026/05/28",
      "open": 110.0,
      "high": 112.0,
      "low": 107.0,
      "close": 110.0,
      "volume": 82082,
      "MA5": 103.26,
      "MA10": 99.67,
      "MA20": 96.62
    },
    {
      "date": "2026/05/27",
      "open": 104.5,
      "high": 110.0,
      "low": 103.0,
      "close": 110.0,
      "volume": 93027,
      "MA5": 100.48,
      "MA10": 98.13,
      "MA20": 95.69
    },
    {
      "date": "2026/05/26",
      "open": 97.8,
      "high": 103.5,
      "low": 97.8,
      "close": 103.5,
      "volume": 103318,
      "MA5": 97.64,
      "MA10": 96.6,
      "MA20": 94.61
    },
    {
      "date": "2026/05/25",
      "open": 95.4,
      "high": 97.7,
      "low": 94.7,
      "close": 97.7,
      "volume": 47023,
      "MA5": 96.38,
      "MA10": 95.62,
      "MA20": 93.84
    },
    {
      "date": "2026/05/22",
      "open": 95.4,
      "high": 96.0,
      "low": 94.3,
      "close": 95.1,
      "volume": 41801,
      "MA5": 95.88,
      "MA10": 95.4,
      "MA20": 93.34
    },
    {
      "date": "2026/05/21",
      "open": 96.5,
      "high": 96.8,
      "low": 95.3,
      "close": 96.1,
      "volume": 32176,
      "MA5": 96.08,
      "MA10": 95.56,
      "MA20": 93.0
    },
    {
      "date": "2026/05/20",
      "open": 97.1,
      "high": 97.2,
      "low": 95.6,
      "close": 95.8,
      "volume": 29549,
      "MA5": 95.78,
      "MA10": 95.4,
      "MA20": 92.61
    },
    {
      "date": "2026/05/19",
      "open": 95.7,
      "high": 98.1,
      "low": 95.5,
      "close": 97.2,
      "volume": 36306,
      "MA5": 95.56,
      "MA10": 95.1,
      "MA20": 92.2
    },
    {
      "date": "2026/05/18",
      "open": 96.3,
      "high": 96.6,
      "low": 94.5,
      "close": 95.2,
      "volume": 25769,
      "MA5": 94.86,
      "MA10": 94.6,
      "MA20": 91.7
    },
    {
      "date": "2026/05/15",
      "open": 96.5,
      "high": 98.6,
      "low": 95.0,
      "close": 96.1,
      "volume": 100424,
      "MA5": 94.92,
      "MA10": 94.18,
      "MA20": 91.34
    },
    {
      "date": "2026/05/14",
      "open": 93.9,
      "high": 96.0,
      "low": 93.9,
      "close": 94.6,
      "volume": 20009,
      "MA5": 95.04,
      "MA10": 93.57,
      "MA20": 90.94
    },
    {
      "date": "2026/05/13",
      "open": 93.5,
      "high": 95.2,
      "low": 93.3,
      "close": 94.7,
      "volume": 18416,
      "MA5": 95.02,
      "MA10": 93.24,
      "MA20": 90.58
    },
    {
      "date": "2026/05/12",
      "open": 96.0,
      "high": 96.0,
      "low": 93.7,
      "close": 93.7,
      "volume": 36169,
      "MA5": 94.64,
      "MA10": 92.63,
      "MA20": 90.22
    },
    {
      "date": "2026/05/11",
      "open": 96.7,
      "high": 96.7,
      "low": 95.5,
      "close": 95.5,
      "volume": 22797,
      "MA5": 94.34,
      "MA10": 92.05,
      "MA20": 89.88
    },
    {
      "date": "2026/05/08",
      "open": 94.5,
      "high": 96.9,
      "low": 94.1,
      "close": 96.7,
      "volume": 58348,
      "MA5": 93.44,
      "MA10": 91.28,
      "MA20": 89.48
    },
    {
      "date": "2026/05/07",
      "open": 93.3,
      "high": 94.8,
      "low": 92.5,
      "close": 94.5,
      "volume": 35427,
      "MA5": 92.1,
      "MA10": 90.44,
      "MA20": 89.07
    },
    {
      "date": "2026/05/06",
      "open": 93.0,
      "high": 94.0,
      "low": 92.4,
      "close": 92.8,
      "volume": 24441,
      "MA5": 91.46,
      "MA10": 89.82,
      "MA20": 88.8
    },
    {
      "date": "2026/05/05",
      "open": 91.5,
      "high": 92.3,
      "low": 90.4,
      "close": 92.2,
      "volume": 24852,
      "MA5": 90.62,
      "MA10": 89.31,
      "MA20": 88.55
    },
    {
      "date": "2026/05/04",
      "open": 91.8,
      "high": 94.0,
      "low": 91.0,
      "close": 91.0,
      "volume": 49550,
      "MA5": 89.76,
      "MA10": 88.81
    },
    {
      "date": "2026/04/30",
      "open": 90.4,
      "high": 91.8,
      "low": 90.0,
      "close": 90.0,
      "volume": 31101,
      "MA5": 89.12,
      "MA10": 88.51
    },
    {
      "date": "2026/04/29",
      "open": 89.4,
      "high": 91.3,
      "low": 89.1,
      "close": 91.3,
      "volume": 38229,
      "MA5": 88.78,
      "MA10": 88.3
    },
    {
      "date": "2026/04/28",
      "open": 88.5,
      "high": 89.2,
      "low": 88.1,
      "close": 88.6,
      "volume": 21109,
      "MA5": 88.18,
      "MA10": 87.92
    },
    {
      "date": "2026/04/27",
      "open": 87.5,
      "high": 88.5,
      "low": 87.2,
      "close": 87.9,
      "volume": 24301,
      "MA5": 88.0,
      "MA10": 87.82
    },
    {
      "date": "2026/04/24",
      "open": 88.2,
      "high": 88.7,
      "low": 87.8,
      "close": 87.8,
      "volume": 16799,
      "MA5": 87.86,
      "MA10": 87.7
    },
    {
      "date": "2026/04/23",
      "open": 88.2,
      "high": 89.2,
      "low": 88.1,
      "close": 88.3,
      "volume": 26420,
      "MA5": 87.9,
      "MA10": 87.68
    },
    {
      "date": "2026/04/22",
      "open": 87.8,
      "high": 88.8,
      "low": 87.7,
      "close": 88.3,
      "volume": 23952,
      "MA5": 87.82,
      "MA10": 87.7
    },
    {
      "date": "2026/04/21",
      "open": 88.1,
      "high": 88.1,
      "low": 87.2,
      "close": 87.7,
      "volume": 18530,
      "MA5": 87.66,
      "MA10": 87.79
    },
    {
      "date": "2026/04/20",
      "open": 87.9,
      "high": 88.0,
      "low": 87.2,
      "close": 87.2,
      "volume": 22352,
      "MA5": 87.64,
      "MA10": 87.79
    },
    {
      "date": "2026/04/17",
      "open": 88.0,
      "high": 88.0,
      "low": 86.8,
      "close": 88.0,
      "volume": 24660,
      "MA5": 87.54
    },
    {
      "date": "2026/04/16",
      "open": 87.3,
      "high": 88.4,
      "low": 87.2,
      "close": 87.9,
      "volume": 21047,
      "MA5": 87.46
    },
    {
      "date": "2026/04/15",
      "open": 88.0,
      "high": 88.4,
      "low": 87.1,
      "close": 87.5,
      "volume": 21344,
      "MA5": 87.58
    },
    {
      "date": "2026/04/14",
      "open": 86.7,
      "high": 88.4,
      "low": 86.7,
      "close": 87.6,
      "volume": 18208,
      "MA5": 87.92
    },
    {
      "date": "2026/04/13",
      "open": 87.5,
      "high": 87.6,
      "low": 86.7,
      "close": 86.7,
      "volume": 17475,
      "MA5": 87.94
    },
    {
      "date": "2026/04/10",
      "open": 87.5,
      "high": 88.2,
      "low": 87.3,
      "close": 87.6,
      "volume": 20801
    },
    {
      "date": "2026/04/09",
      "open": 89.2,
      "high": 89.2,
      "low": 87.6,
      "close": 88.5,
      "volume": 21410
    },
    {
      "date": "2026/04/08",
      "open": 89.2,
      "high": 89.2,
      "low": 87.9,
      "close": 89.2,
      "volume": 17573
    },
    {
      "date": "2026/04/07",
      "open": 87.9,
      "high": 88.3,
      "low": 86.5,
      "close": 87.7,
      "volume": 14257
    }
  ]
}