{
  "meta": {
    "stock_id": "3231",
    "name": "緯創",
    "source": "TWSE daily (twse/2026/)",
    "period": "~40 trading days",
    "date_range": "20260410~20260605",
    "count": 40,
    "format_note": "AI-readable OHLC data. date(YYYY/MM/DD), open/high/low/close(float), volume(int, 張). Bullish=close>open, Bearish=close<open."
  },
  "data": [
    {
      "date": "2026/06/05",
      "open": 172.5,
      "high": 174.0,
      "low": 165.5,
      "close": 171.0,
      "volume": 75786,
      "MA5": 181.2,
      "MA10": 164.9,
      "MA20": 151.43
    },
    {
      "date": "2026/06/04",
      "open": 188.0,
      "high": 189.0,
      "low": 176.0,
      "close": 176.0,
      "volume": 128624,
      "MA5": 178.7,
      "MA10": 162.25,
      "MA20": 150.2
    },
    {
      "date": "2026/06/03",
      "open": 193.0,
      "high": 201.0,
      "low": 188.0,
      "close": 194.0,
      "volume": 175481,
      "MA5": 172.4,
      "MA10": 158.65,
      "MA20": 148.7
    },
    {
      "date": "2026/06/02",
      "open": 179.0,
      "high": 191.0,
      "low": 177.0,
      "close": 191.0,
      "volume": 282187,
      "MA5": 162.6,
      "MA10": 152.5,
      "MA20": 146.32
    },
    {
      "date": "2026/06/01",
      "open": 174.0,
      "high": 174.0,
      "low": 172.5,
      "close": 174.0,
      "volume": 94609,
      "MA5": 153.6,
      "MA10": 146.65,
      "MA20": 143.88
    },
    {
      "date": "2026/05/29",
      "open": 154.0,
      "high": 158.5,
      "low": 153.0,
      "close": 158.5,
      "volume": 112534,
      "MA5": 148.6,
      "MA10": 142.8,
      "MA20": 142.2
    },
    {
      "date": "2026/05/28",
      "open": 146.0,
      "high": 149.0,
      "low": 143.0,
      "close": 144.5,
      "volume": 40975,
      "MA5": 145.8,
      "MA10": 140.5,
      "MA20": 141.12
    },
    {
      "date": "2026/05/27",
      "open": 147.5,
      "high": 148.5,
      "low": 143.5,
      "close": 145.0,
      "volume": 37563,
      "MA5": 144.9,
      "MA10": 139.85,
      "MA20": 140.93
    },
    {
      "date": "2026/05/26",
      "open": 149.5,
      "high": 149.5,
      "low": 145.5,
      "close": 146.0,
      "volume": 35795,
      "MA5": 142.4,
      "MA10": 139.4,
      "MA20": 140.7
    },
    {
      "date": "2026/05/25",
      "open": 148.5,
      "high": 150.5,
      "low": 147.0,
      "close": 149.0,
      "volume": 70126,
      "MA5": 139.7,
      "MA10": 138.95,
      "MA20": 140.53
    },
    {
      "date": "2026/05/22",
      "open": 142.5,
      "high": 146.0,
      "low": 139.5,
      "close": 144.5,
      "volume": 70277,
      "MA5": 137.0,
      "MA10": 137.95,
      "MA20": 140.15
    },
    {
      "date": "2026/05/21",
      "open": 134.5,
      "high": 141.5,
      "low": 134.0,
      "close": 140.0,
      "volume": 53678,
      "MA5": 135.2,
      "MA10": 138.15,
      "MA20": 139.9
    },
    {
      "date": "2026/05/20",
      "open": 134.0,
      "high": 135.5,
      "low": 132.0,
      "close": 132.5,
      "volume": 20642,
      "MA5": 134.8,
      "MA10": 138.75,
      "MA20": 140.1
    },
    {
      "date": "2026/05/19",
      "open": 135.5,
      "high": 136.0,
      "low": 132.5,
      "close": 132.5,
      "volume": 25581,
      "MA5": 136.4,
      "MA10": 140.15,
      "MA20": 140.7
    },
    {
      "date": "2026/05/18",
      "open": 135.0,
      "high": 136.5,
      "low": 132.0,
      "close": 135.5,
      "volume": 29121,
      "MA5": 138.2,
      "MA10": 141.1,
      "MA20": 141.1
    },
    {
      "date": "2026/05/15",
      "open": 139.5,
      "high": 144.0,
      "low": 135.0,
      "close": 135.5,
      "volume": 67278,
      "MA5": 138.9,
      "MA10": 141.6,
      "MA20": 141.15
    },
    {
      "date": "2026/05/14",
      "open": 140.5,
      "high": 141.5,
      "low": 138.0,
      "close": 138.0,
      "volume": 42377,
      "MA5": 141.1,
      "MA10": 141.75,
      "MA20": 141.07
    },
    {
      "date": "2026/05/13",
      "open": 139.0,
      "high": 141.5,
      "low": 138.0,
      "close": 140.5,
      "volume": 26883,
      "MA5": 142.7,
      "MA10": 142.0,
      "MA20": 140.82
    },
    {
      "date": "2026/05/12",
      "open": 139.0,
      "high": 143.0,
      "low": 135.5,
      "close": 141.5,
      "volume": 75965,
      "MA5": 143.9,
      "MA10": 142.0,
      "MA20": 140.62
    },
    {
      "date": "2026/05/11",
      "open": 147.0,
      "high": 147.0,
      "low": 138.0,
      "close": 139.0,
      "volume": 114217,
      "MA5": 144.0,
      "MA10": 142.1,
      "MA20": 140.28
    },
    {
      "date": "2026/05/08",
      "open": 146.0,
      "high": 149.0,
      "low": 143.5,
      "close": 146.5,
      "volume": 44206,
      "MA5": 144.3,
      "MA10": 142.35,
      "MA20": 140.07
    },
    {
      "date": "2026/05/07",
      "open": 148.5,
      "high": 149.0,
      "low": 143.5,
      "close": 146.0,
      "volume": 43321,
      "MA5": 142.4,
      "MA10": 141.65
    },
    {
      "date": "2026/05/06",
      "open": 143.5,
      "high": 146.5,
      "low": 142.5,
      "close": 146.5,
      "volume": 71828,
      "MA5": 141.3,
      "MA10": 141.45
    },
    {
      "date": "2026/05/05",
      "open": 140.5,
      "high": 142.5,
      "low": 139.0,
      "close": 142.0,
      "volume": 24899,
      "MA5": 140.1,
      "MA10": 141.25
    },
    {
      "date": "2026/05/04",
      "open": 138.5,
      "high": 141.0,
      "low": 138.0,
      "close": 140.5,
      "volume": 23500,
      "MA5": 140.2,
      "MA10": 141.1
    },
    {
      "date": "2026/04/30",
      "open": 139.5,
      "high": 140.5,
      "low": 136.0,
      "close": 137.0,
      "volume": 26873,
      "MA5": 140.4,
      "MA10": 140.7
    },
    {
      "date": "2026/04/29",
      "open": 139.0,
      "high": 140.5,
      "low": 136.5,
      "close": 140.5,
      "volume": 23368,
      "MA5": 140.9,
      "MA10": 140.4
    },
    {
      "date": "2026/04/28",
      "open": 143.5,
      "high": 144.5,
      "low": 140.0,
      "close": 140.5,
      "volume": 27611,
      "MA5": 141.6,
      "MA10": 139.65
    },
    {
      "date": "2026/04/27",
      "open": 143.0,
      "high": 144.0,
      "low": 141.0,
      "close": 142.5,
      "volume": 38390,
      "MA5": 142.4,
      "MA10": 139.25
    },
    {
      "date": "2026/04/24",
      "open": 140.5,
      "high": 141.5,
      "low": 138.0,
      "close": 141.5,
      "volume": 40785,
      "MA5": 142.0,
      "MA10": 138.45
    },
    {
      "date": "2026/04/23",
      "open": 145.0,
      "high": 146.0,
      "low": 135.0,
      "close": 139.5,
      "volume": 63203,
      "MA5": 141.0,
      "MA10": 137.8
    },
    {
      "date": "2026/04/22",
      "open": 145.0,
      "high": 145.5,
      "low": 143.0,
      "close": 144.0,
      "volume": 50378,
      "MA5": 139.9
    },
    {
      "date": "2026/04/21",
      "open": 142.0,
      "high": 145.5,
      "low": 141.5,
      "close": 144.5,
      "volume": 86280,
      "MA5": 137.7
    },
    {
      "date": "2026/04/20",
      "open": 137.0,
      "high": 141.0,
      "low": 135.5,
      "close": 140.5,
      "volume": 79145,
      "MA5": 136.1
    },
    {
      "date": "2026/04/17",
      "open": 133.0,
      "high": 137.0,
      "low": 132.5,
      "close": 136.5,
      "volume": 36847,
      "MA5": 134.9
    },
    {
      "date": "2026/04/16",
      "open": 134.0,
      "high": 135.5,
      "low": 131.5,
      "close": 134.0,
      "volume": 35493,
      "MA5": 134.6
    },
    {
      "date": "2026/04/15",
      "open": 137.5,
      "high": 138.0,
      "low": 132.0,
      "close": 133.0,
      "volume": 39441
    },
    {
      "date": "2026/04/14",
      "open": 137.0,
      "high": 139.0,
      "low": 136.0,
      "close": 136.5,
      "volume": 38753
    },
    {
      "date": "2026/04/13",
      "open": 135.0,
      "high": 136.5,
      "low": 132.5,
      "close": 134.5,
      "volume": 26991
    },
    {
      "date": "2026/04/10",
      "open": 134.0,
      "high": 136.5,
      "low": 133.0,
      "close": 135.0,
      "volume": 42081
    }
  ]
}